tesseract/__init__.py
tesseract/_logging.py
tesseract/error_pb2.py
tesseract/error_pb2_grpc.py
tesseract/extract.py
tesseract/features.py
tesseract/features_pb2.py
tesseract/inference_pb2.py
tesseract/inference_pb2_grpc.py
tesseract/server.py
tesseract/tensor.py
tesseract/validate.py
tesseract/scripts/validate.py
tesseract_sdk-0.9.1.dist-info/LICENSE
tesseract_sdk-0.9.1.dist-info/METADATA
tesseract_sdk-0.9.1.dist-info/WHEEL
tesseract_sdk-0.9.1.dist-info/entry_points.txt
tesseract_sdk-0.9.1.dist-info/top_level.txt
tesseract_sdk-0.9.1.dist-info/RECORD
