Metadata-Version: 2.1
Name: tesseract-sdk
Version: 0.9.1
Summary: Python SDK for Tesseract Models
Author-email: The SeerAI Team <contact@seer.ai>
License: Apache License
Project-URL: Homepage, https://docs.seer.ai/geodesic-web
Keywords: geodesic,analysis,seerai,data,science,tesseract
Classifier: Programming Language :: Python
Classifier: Operating System :: OS Independent
Classifier: Intended Audience :: Developers
Classifier: Intended Audience :: Science/Research
Classifier: Topic :: Scientific/Engineering :: GIS
Classifier: Topic :: Scientific/Engineering :: Visualization
Classifier: Topic :: Scientific/Engineering :: Artificial Intelligence
Classifier: Topic :: Software Development :: Libraries :: Python Modules
Classifier: License :: OSI Approved :: Apache Software License
Requires-Python: >=3.8
License-File: LICENSE
Requires-Dist: geodesic-api >=0.12.0
Requires-Dist: grpclib >=0.4.2
Requires-Dist: protobuf >=3.20.0
Requires-Dist: grpcio >=1.50.0
Requires-Dist: docker <7.0.0,>=6.1.0
Provides-Extra: all
Requires-Dist: tesseract-sdk[extract] ; extra == 'all'
Provides-Extra: dev
Requires-Dist: tesseract-sdk[all] ; extra == 'dev'
Requires-Dist: grpcio-tools ; extra == 'dev'
Requires-Dist: matplotlib >=3.4.3 ; extra == 'dev'
Requires-Dist: networkx ; extra == 'dev'
Requires-Dist: zarr ; extra == 'dev'
Requires-Dist: fsspec ; extra == 'dev'
Requires-Dist: gcsfs ; extra == 'dev'
Requires-Dist: pytest >=6.2.5 ; extra == 'dev'
Requires-Dist: coverage >=5.5 ; extra == 'dev'
Requires-Dist: ruff ; extra == 'dev'
Requires-Dist: pre-commit ; extra == 'dev'
Provides-Extra: extract
Requires-Dist: scikit-image >=0.10.0 ; extra == 'extract'
